pytest_xlsx/settings.cpython-312-darwin.so
pytest_xlsx/__init__.cpython-312-darwin.so
pytest_xlsx/plugin.cpython-312-darwin.so
pytest_xlsx/funcs.cpython-312-darwin.so
pytest_xlsx/templates.cpython-312-darwin.so
pytest_xlsx/__init__.pyi
pytest_xlsx/file.cpython-312-darwin.so
pytest_xlsx/models.cpython-312-darwin.so
pytest_xlsx/_plugin.cpython-312-darwin.so
pytest_xlsx/templates.pyi
pytest_xlsx/settings.pyi
pytest_xlsx/models.pyi
pytest_xlsx/fixtures.pyi
pytest_xlsx/hooks.pyi
pytest_xlsx/funcs.pyi
pytest_xlsx/fixtures.cpython-312-darwin.so
pytest_xlsx/plugin.pyi
pytest_xlsx/hooks.cpython-312-darwin.so
pytest_xlsx/file.pyi
pytest_xlsx/_plugin.pyi
pytest_xlsx-2.0.0.dist-info/RECORD
pytest_xlsx-2.0.0.dist-info/WHEEL
pytest_xlsx-2.0.0.dist-info/entry_points.txt
pytest_xlsx-2.0.0.dist-info/METADATA
