Metadata-Version: 2.1
Name: pytest-xlsx
Version: 2.0.0
Summary: pytest plugin for generating test cases by xlsx(excel)
Author: dongfangtianyu
Requires-Python: >=3.12,<3.13
Requires-Dist: allure-pytest>=2.13.5
Requires-Dist: jinja2>=3.1.4
Requires-Dist: openpyxl>=3.0.10
Requires-Dist: pydantic<3,>=2.0
Requires-Dist: pytest~=8.2.2
Requires-Dist: pyyaml>=6.0
Requires-Dist: tabulate[widechars]>=0.9.0
Requires-Dist: wcwidth>=0.2.5
Project-URL: Homepage, https://github.com/dongfangtianyu/pytest-xlsx
